ml-deploy-lite/__init__.py
ml-deploy-lite/api.py
ml-deploy-lite/docker.py
ml-deploy-lite/k8s.py
ml-deploy-lite/monitoring.py
ml_deploy_lite/__init__.py
ml_deploy_lite/api.py
ml_deploy_lite/docker.py
ml_deploy_lite/k8s.py
ml_deploy_lite/monitoring.py
ml_deploy_lite-0.7.1.dist-info/METADATA
ml_deploy_lite-0.7.1.dist-info/WHEEL
ml_deploy_lite-0.7.1.dist-info/top_level.txt
ml_deploy_lite-0.7.1.dist-info/RECORD
