Metadata-Version: 2.1
Name: ml_deploy_lite
Version: 0.7.1
Summary: A library to simplify your ML model deployments
Home-page: https://github.com/Blacksujit/ML-Deploy-Lite.git
Author: Sujit Nirmal (@blacksujit)
Author-email: nirmalsujit981@gmail.com
Keywords: Python,Machine Learning,Deep Learning,MLops,Deployements,Model-Deployement,ML-models,state-of-art-deployements
Classifier: Intended Audience :: Developers
Classifier: Development Status :: 3 - Alpha
Classifier: Programming Language :: Python :: 3
Classifier: Programming Language :: Python :: 3.6
Classifier: Programming Language :: Python :: 3.7
Classifier: Programming Language :: Python :: 3.8
Classifier: Programming Language :: Python :: 3.9
Classifier: License :: OSI Approved :: MIT License
Classifier: Operating System :: OS Independent
Classifier: Operating System :: OS Independent
Classifier: Topic :: Software Development :: Libraries :: Python Modules
Requires-Python: >=3.6
Requires-Dist: Flask
Requires-Dist: gunicorn
Requires-Dist: docker
Requires-Dist: pyyaml
Requires-Dist: joblib
Requires-Dist: scikit-learn
Requires-Dist: prometheus-flask-exporter
